{
  "id": "mem_20251204134125207249",
  "intent": "Iterative self-improvement in research tasks",
  "content": {
    "lesson": "Implementing a self-improvement loop can significantly enhance the efficiency and accuracy of research tasks.",
    "source_task": "Research: current state of quantum computing in 2024",
    "source_result": "Achieved 9/10 in 1 iterations. Key approach: self-improvement loop.",
    "was_successful": true
  },
  "sense_patterns": [
    "research",
    "quantum computing",
    "2024",
    "self-improvement",
    "iterative process",
    "current state analysis"
  ],
  "tension": 0.8,
  "success_rate": 0.5,
  "times_used": 0,
  "created_at": "2025-12-04T13:41:25.207343",
  "last_activated": null
}